aasp/__init__.py
aasp/predictor.py
aasp/trainer.py
aasp/models/__init__.py
aasp/models/aasp_dataset.py
aasp/models/data_handler.py
aasp/models/example_model.py
aasp/models/model_interface.py
aasp-0.1.1.dist-info/licenses/LICENSE
aasp-0.1.1.dist-info/METADATA
aasp-0.1.1.dist-info/WHEEL
aasp-0.1.1.dist-info/top_level.txt
aasp-0.1.1.dist-info/RECORD
