Metadata-Version: 2.4
Name: aasp
Version: 0.1.1
Summary: Add your description here
Requires-Python: >=3.13.7
License-File: LICENSE
Requires-Dist: ipykernel>=7.1.0
Requires-Dist: matplotlib>=3.10.7
Requires-Dist: numpy>=2.3.4
Requires-Dist: pandas>=2.3.3
Requires-Dist: pylint>=4.0.3
Requires-Dist: pyyaml>=6.0.3
Requires-Dist: scikit-learn>=1.7.2
Requires-Dist: tqdm>=4.67.1
Dynamic: license-file
